LICENSE
MANIFEST.in
README.md
setup.cfg
setup.py
ekankthkx/__init__.py
ekankthkx/config.py
ekankthkx.egg-info/PKG-INFO
ekankthkx.egg-info/SOURCES.txt
ekankthkx.egg-info/dependency_links.txt
ekankthkx.egg-info/requires.txt
ekankthkx.egg-info/top_level.txt
ekankthkx/Clients/__init__.py
ekankthkx/Clients/client.py
ekankthkx/Clients/pytgcalls.py
ekankthkx/blacklist/__init__.py
ekankthkx/blacklist/support.py
ekankthkx/button/__init__.py
ekankthkx/button/button.py
ekankthkx/extra/__init__.py
ekankthkx/extra/hosted.py
ekankthkx/help/__init__.py
ekankthkx/help/help.py
ekankthkx/helper/__init__.py
ekankthkx/helper/basic.py
ekankthkx/helper/call.py
ekankthkx/helper/data.py
ekankthkx/helper/ekankth.py
ekankthkx/helper/goblok.py
ekankthkx/helper/hacking.py
ekankthkx/helper/inline.py
ekankthkx/helper/interval.py
ekankthkx/helper/parser.py
ekankthkx/helper/repo.py
ekankthkx/helper/sticker.py
ekankthkx/helper/tools.py
ekankthkx/helper/utility.py
ekankthkx/helper/what.py
ekankthkx/methods/__init__.py
ekankthkx/methods/queue.py
ekankthkx/py_trans/__init__.py
ekankthkx/py_trans/async_translator.py
ekankthkx/py_trans/errors.py
ekankthkx/py_trans/language_codes.py
ekankthkx/py_trans/translator.py
ekankthkx/pyrogram/__init__.py
ekankthkx/pyrogram/_wrappers.py
ekankthkx/pyrogram/func.py
ekankthkx/pyrogram/misc.py
ekankthkx/pyrogram/sections.py
ekankthkx/pyrogram/toolbot.py
ekankthkx/pyrogram/tools.py